build
rkd
