Metadata-Version: 2.1
Name: rkd.process
Version: 2.4.0.0b2.dev68
Summary: rkd.process provides easy process interaction and output capturing/redirecting, wraps subprocess from Python's standard library.
Home-page: https://github.com/riotkit-org
Author: RiotKit non-profit organization
Author-email: riotkit@riseup.net
License: Apache-2
Keywords: rkd,riotkit,anarchism,output capturing,output,subprocess
Platform: UNKNOWN
Classifier: Development Status :: 5 - Production/Stable
Classifier: Environment :: Console
Classifier: Intended Audience :: Developers
Classifier: Intended Audience :: System Administrators
Classifier: Intended Audience :: Information Technology
Classifier: License :: OSI Approved :: Apache Software License
Classifier: Operating System :: POSIX
Classifier: Programming Language :: Python :: 3 :: Only
